xapi_guard_middleware/__init__.py
xapi_guard_middleware/error_codes.py
xapi_guard_middleware/middleware.py
xapi_guard_middleware-1.0.6.dist-info/LICENSE
xapi_guard_middleware-1.0.6.dist-info/METADATA
xapi_guard_middleware-1.0.6.dist-info/WHEEL
xapi_guard_middleware-1.0.6.dist-info/RECORD
