Metadata-Version: 2.1
Name: xapi-guard-middleware
Version: 1.0.6
Summary: XAPI Guard is a FastAPI middleware that protects your API endpoints by validating X-API-Key header.
License: MIT
Author: Abdullah Alqahtani
Author-email: anqorithm@protonmail.com
Requires-Python: >=3.11,<4.0
Classifier: License :: OSI Approved :: MIT License
Classifier: Programming Language :: Python :: 3
Classifier: Programming Language :: Python :: 3.11
Classifier: Programming Language :: Python :: 3.12
Requires-Dist: fastapi (>=0.109.0,<0.115.8)
